Metadata-Version: 1.0
Name: packager
Version: 0.2.0
Summary: C/C++ package manager built on the top of gyp
Home-page: https://github.com/packager/packager
Author: Abel Lucas
Author-email: ylilt71@gmail.com
License: UNKNOWN
Platform: UNKNOWN
